setuptools_metadata-0.1.5.dist-info/RECORD
setuptools_metadata-0.1.5.dist-info/WHEEL
setuptools_metadata-0.1.5.dist-info/metadata.json
setuptools_metadata-0.1.5.dist-info/DESCRIPTION.rst
setuptools_metadata-0.1.5.dist-info/METADATA
setuptools_metadata-0.1.5.dist-info/top_level.txt
setuptools_metadata-0.1.5.dist-info/entry_points.txt
setuptools_metadata/__init__.py
