Metadata-Version: 2.0
Name: setuptools-metadata
Version: 0.1.5
Summary: Adds a command to setup.py for displaying metadata about the package.
Home-page: https://github.com/j0057/setuptools-metadata
Author: Joost Molenaar
Author-email: j.j.molenaar@gmail.com
License: UNKNOWN
Platform: UNKNOWN
